{
  "devices": {
    "macs": {
      "M1 TFPSERVER": {
        "last_updated": "2025-01-20T15:19:23Z",
        "device_type": "mac_mini",
        "device_name": "M1 TFPSERVER",
        "system_info": {
          "temperature": 0,
          "power": {
            "on_ac_power": true,
            "ups_charging": false,
            "ups_connected": true,
            "ups_percentage": 100,
            "estimated_runtime": 297
          },
          "storage": {
            "external_drives": [
              {
                "used_space": 14042898685952,
                "available_space": 1957792219136,
                "mount_point": "/Volumes/8T",
                "total_space": 16000690905088,
                "name": "8T"
              }
            ],
            "boot_drive": 0
          },
          "os_version": "15.2-24C101",
          "build_number": "24C101",
          "metrics": {
            "gpu_frequency": {},
            "memory_percentage": 36.7,
            "memory_total": 16,
            "total_power": 0.46,
            "cpu_frequency": {},
            "memory_used": 5.88,
            "cpu_usage": 132.8,
            "cpu_power": 0.46,
            "gpu_power": 0
          }
        }
      },
      "m3FIFTEEN": {
        "system_info": {
          "display": {
            "supports_dual_4k": true,
            "external_displays": 1,
            "built_in": true
          },
          "storage": {
            "internal_drive": {
              "used_space": 444203991040,
              "available_space": 1551014174720,
              "mount_point": "/",
              "total_space": 1995218165760,
              "name": "Internal"
            }
          },
          "os_version": "15.2-24C101",
          "temperature": 0,
          "metrics": {
            "memory_total": 24,
            "memory_percentage": 44.9,
            "total_power": 0.1,
            "memory_used": 10.79,
            "cpu_usage": 42.4,
            "cpu_power": 0.1,
            "gpu_power": 0
          },
          "battery": {
            "percentage": 71,
            "is_charging": true
          },
          "build_number": "24C101"
        },
        "last_updated": "2025-01-20T08:36:01Z",
        "device_type": "mac",
        "device_name": "m3FIFTEEN"
      }
    },
    "ipads": {
      "M1P45Db": {
        "system_info": {
          "storage": {
            "boot_drive": 0
          },
          "model": "iPad Pro (12.9-inch) (5th generation)",
          "os_version": "18.3",
          "battery": {
            "charging": false,
            "percentage": 70
          }
        },
        "device_model": "iPad Pro (12.9-inch) (5th generation)",
        "symbol": "ipad",
        "last_updated": "2025-01-20T11:23:01.879Z",
        "device_name": "M1P45Db",
        "device_type": "ipad"
      },
      "m4eleven": {
        "system_info": {
          "storage": {
            "boot_drive": 0
          },
          "model": "iPad Pro 11-inch (M4)",
          "os_version": "18.2.1",
          "battery": {
            "charging": false,
            "percentage": 70
          }
        },
        "device_model": "iPad Pro 11-inch (M4)",
        "symbol": "ipad.landscape",
        "last_updated": "2025-01-19T08:01:59.696Z",
        "device_type": "ipad",
        "device_name": "m4eleven"
      }
    },
    "iphones": {
      "MiniProductRed13": {
        "system_info": {
          "storage": {
            "boot_drive": 0
          },
          "model": "iPhone 13 mini",
          "os_version": "18.3",
          "battery": {
            "charging": false,
            "percentage": 70
          }
        },
        "device_model": "iPhone 13 mini",
        "symbol": "iphone.gen2",
        "last_updated": "2025-01-20T12:13:42.219Z",
        "device_type": "iphone",
        "device_name": "MiniProductRed13"
      },
      "A18p tfp.la/stirling": {
        "device_name": "A18p tfp.la/stirling",
        "device_type": "iphone",
        "symbol": "iphone.gen3",
        "device_model": "iPhone 16 Pro",
        "system_info": {
          "os_version": "18.2.1",
          "model": "iPhone 16 Pro",
          "battery": {
            "percentage": 60,
            "charging": false
          },
          "storage": {
            "boot_drive": 0
          }
        },
        "last_updated": "2025-01-20T15:21:33.057Z"
      }
    }
  },
  "last_updated": "2025-01-20T15:21:33.057Z"
}