{
  "devices": {
    "macs": {},
    "ipads": {},
    "iphones": {
      "MiniProductRed13": {
        "device_name": "MiniProductRed13",
        "device_type": "iphone",
        "device_model": "Mini 13",
        "system_info": {
          "os_version": "18.3",
          "model": "Mini 13",
          "battery": {
            "percentage": 50,
            "charging": false
          },
          "storage": {
            "boot_drive": 0
          }
        },
        "last_updated": "2025-01-04T14:21:31.137Z"
      },
      "iPhone": {
        "device_name": "iPhone",
        "device_type": "iphone",
        "device_model": "iPhone",
        "system_info": {
          "os_version": "18.3",
          "model": "iPhone",
          "battery": {
            "percentage": 45,
            "charging": false
          },
          "storage": {
            "boot_drive": 0
          }
        },
        "last_updated": "2025-01-04T14:56:21.450Z"
      }
    }
  },
  "last_updated": 1736002581450
}